{
  "type": "FeatureCollection",
  "features": [
    {
      "type": "Feature",
      "properties": {},
      "geometry": {
        "type": "LineString",
        "coordinates": [
          [
            28.29039,
            -25.7845906
          ],
          [
            28.2903681,
            -25.7846947
          ],
          [
            28.2903058,
            -25.7854899
          ],
          [
            28.2902523,
            -25.7862291
          ],
          [
            28.290275,
            -25.7864432
          ],
          [
            28.2903655,
            -25.7867184
          ],
          [
            28.2904618,
            -25.7869172
          ],
          [
            28.290626,
            -25.7871874
          ],
          [
            28.2913322,
            -25.7874653
          ],
          [
            28.2930573,
            -25.7881256
          ],
          [
            28.2944578,
            -25.7886662
          ],
          [
            28.2967178,
            -25.7895179
          ],
          [
            28.2974594,
            -25.7904864
          ],
          [
            28.298326,
            -25.7913235
          ],
          [
            28.2996887,
            -25.7925469
          ],
          [
            28.2999831,
            -25.7927355
          ],
          [
            28.3012342,
            -25.7936886
          ],
          [
            28.3022476,
            -25.7944634
          ],
          [
            28.3026817,
            -25.7948018
          ],
          [
            28.3031969,
            -25.7950923
          ],
          [
            28.3036724,
            -25.795337
          ],
          [
            28.3040687,
            -25.7955052
          ],
          [
            28.3048046,
            -25.7958467
          ],
          [
            28.305725,
            -25.7962555
          ],
          [
            28.3069559,
            -25.7968075
          ],
          [
            28.3074032,
            -25.7970215
          ],
          [
            28.3076749,
            -25.7971795
          ],
          [
            28.3078844,
            -25.7973477
          ],
          [
            28.3080089,
            -25.7976179
          ],
          [
            28.3081945,
            -25.7979069
          ],
          [
            28.308302,
            -25.7981923
          ],
          [
            28.3083926,
            -25.7988091
          ],
          [
            28.3085172,
            -25.799594
          ],
          [
            28.308611,
            -25.800151
          ],
          [
            28.3087185,
            -25.8004313
          ],
          [
            28.3090469,
            -25.8009512
          ],
          [
            28.3094948,
            -25.801555
          ],
          [
            28.3099647,
            -25.8022481
          ],
          [
            28.3101741,
            -25.8025692
          ],
          [
            28.3107435,
            -25.8034303
          ],
          [
            28.3116153,
            -25.8029614
          ],
          [
            28.3133986,
            -25.801993
          ],
          [
            28.3142176,
            -25.8015222
          ],
          [
            28.3150328,
            -25.8010737
          ],
          [
            28.3158232,
            -25.8005984
          ],
          [
            28.3175346,
            -25.79957
          ],
          [
            28.3183813,
            -25.8002702
          ],
          [
            28.3192192,
            -25.8009277
          ],
          [
            28.3199372,
            -25.8015353
          ],
          [
            28.3208132,
            -25.8022731
          ],
          [
            28.3216251,
            -25.802978
          ],
          [
            28.3227547,
            -25.8039218
          ],
          [
            28.3236888,
            -25.8047118
          ],
          [
            28.3242981,
            -25.805244
          ],
          [
            28.3243774,
            -25.8053154
          ],
          [
            28.3244227,
            -25.8053561
          ],
          [
            28.3244227,
            -25.8054071
          ],
          [
            28.3244283,
            -25.8054886
          ],
          [
            28.324383,
            -25.8055498
          ],
          [
            28.3242755,
            -25.8056415
          ],
          [
            28.3241679,
            -25.8056823
          ],
          [
            28.3239301,
            -25.8057435
          ],
          [
            28.3239584,
            -25.8059613
          ],
          [
            28.3241,
            -25.806578
          ],
          [
            28.3226748,
            -25.8068495
          ],
          [
            28.3217181,
            -25.8070228
          ],
          [
            28.3200815,
            -25.8073045
          ],
          [
            28.3198041,
            -25.8073708
          ],
          [
            28.3193965,
            -25.8074523
          ],
          [
            28.3191701,
            -25.8075441
          ],
          [
            28.3187568,
            -25.8066675
          ],
          [
            28.3183518,
            -25.8058586
          ],
          [
            28.3200332,
            -25.8055477
          ],
          [
            28.3196571,
            -25.8038588
          ],
          [
            28.3192778,
            -25.8021004
          ],
          [
            28.3189043,
            -25.8022165
          ],
          [
            28.3178891,
            -25.8024902
          ],
          [
            28.3170286,
            -25.8027399
          ],
          [
            28.3160581,
            -25.8030131
          ],
          [
            28.3155769,
            -25.8031507
          ],
          [
            28.3154486,
            -25.8032228
          ],
          [
            28.3151995,
            -25.8034929
          ],
          [
            28.314701,
            -25.8041006
          ],
          [
            28.3141169,
            -25.8047985
          ],
          [
            28.3135481,
            -25.8055188
          ],
          [
            28.3151951,
            -25.8066808
          ],
          [
            28.3145936,
            -25.8073876
          ],
          [
            28.3137728,
            -25.8068525
          ],
          [
            28.3130227,
            -25.8063183
          ],
          [
            28.3122471,
            -25.8058036
          ],
          [
            28.3114772,
            -25.8052786
          ],
          [
            28.3105774,
            -25.8063429
          ],
          [
            28.3099414,
            -25.8071196
          ],
          [
            28.3094733,
            -25.8076928
          ],
          [
            28.3093997,
            -25.8077743
          ],
          [
            28.3092978,
            -25.8078355
          ],
          [
            28.3089298,
            -25.8079017
          ],
          [
            28.307051,
            -25.8082464
          ],
          [
            28.3068925,
            -25.8073647
          ],
          [
            28.3062471,
            -25.8074972
          ],
          [
            28.3061226,
            -25.8075176
          ],
          [
            28.3059754,
            -25.807487
          ],
          [
            28.3058112,
            -25.8073902
          ],
          [
            28.3057376,
            -25.8072985
          ],
          [
            28.3056447,
            -25.807084
          ],
          [
            28.3055145,
            -25.8068801
          ],
          [
            28.3053729,
            -25.8066712
          ],
          [
            28.305305,
            -25.8064979
          ],
          [
            28.3052937,
            -25.8063399
          ],
          [
            28.3053277,
            -25.8060646
          ],
          [
            28.3053988,
            -25.8051366
          ],
          [
            28.3057159,
            -25.8051112
          ],
          [
            28.3061631,
            -25.8050755
          ],
          [
            28.3067405,
            -25.804999
          ],
          [
            28.3076496,
            -25.804841
          ],
          [
            28.3088653,
            -25.8044736
          ],
          [
            28.3098808,
            -25.8039024
          ],
          [
            28.3105658,
            -25.8035354
          ],
          [
            28.3107435,
            -25.8034303
          ]
        ]
      }
    }
  ]
}
